MANIFEST.in
README.txt
setup.py
collective/__init__.py
collective.amberjack.portlet.egg-info/PKG-INFO
collective.amberjack.portlet.egg-info/SOURCES.txt
collective.amberjack.portlet.egg-info/dependency_links.txt
collective.amberjack.portlet.egg-info/entry_points.txt
collective.amberjack.portlet.egg-info/namespace_packages.txt
collective.amberjack.portlet.egg-info/not-zip-safe
collective.amberjack.portlet.egg-info/requires.txt
collective.amberjack.portlet.egg-info/top_level.txt
collective/amberjack/__init__.py
collective/amberjack/portlet/__init__.py
collective/amberjack/portlet/amberjackchoiceportlet.pt
collective/amberjack/portlet/amberjackchoiceportlet.py
collective/amberjack/portlet/bulb.png
collective/amberjack/portlet/completed_tour.gif
collective/amberjack/portlet/configure.zcml
collective/amberjack/portlet/error.png
collective/amberjack/portlet/i18n/collective.amberjack.portlet-plone-es.po
collective/amberjack/portlet/i18n/collective.amberjack.portlet-plone-fr.po
collective/amberjack/portlet/i18n/collective.amberjack.portlet-plone-it.po
collective/amberjack/portlet/i18n/collective.amberjack.portlet-plone-pl.po
collective/amberjack/portlet/i18n/collective.amberjack.portlet-plone.pot
collective/amberjack/portlet/locales/collective.amberjack.portlet-manual.pot
collective/amberjack/portlet/locales/collective.amberjack.portlet.pot
collective/amberjack/portlet/locales/update.sh
collective/amberjack/portlet/locales/es/LC_MESSAGES/collective.amberjack.portlet.po
collective/amberjack/portlet/locales/fr/LC_MESSAGES/collective.amberjack.portlet.po
collective/amberjack/portlet/locales/it/LC_MESSAGES/collective.amberjack.portlet.po
collective/amberjack/portlet/locales/pl/LC_MESSAGES/collective.amberjack.portlet.po
collective/amberjack/portlet/locales/pt-br/LC_MESSAGES/collective.amberjack.portlet.po
collective/amberjack/portlet/locales/sl/LC_MESSAGES/collective.amberjack.portlet-manual.po
collective/amberjack/portlet/locales/sl/LC_MESSAGES/collective.amberjack.portlet.po
collective/amberjack/portlet/profiles/default/jsregistry.xml
collective/amberjack/portlet/profiles/default/metadata.xml
collective/amberjack/portlet/profiles/default/portlets.xml
collective/amberjack/portlet/profiles/default/skins.xml
collective/amberjack/portlet/skins/collective_amberjack_portlet_javascripts/set_aj_cookie.js
collective/amberjack/portlet/tests/__init__.py
collective/amberjack/portlet/tests/base.py
